MANIFEST.in
README.rst
setup.cfg
setup.py
c_to_epl.egg-info/PKG-INFO
c_to_epl.egg-info/SOURCES.txt
c_to_epl.egg-info/dependency_links.txt
c_to_epl.egg-info/entry_points.txt
c_to_epl.egg-info/top_level.txt
ctoepl/__init__.py
ctoepl/_ast_gen.py
ctoepl/_build_tables.py
ctoepl/_c_ast.cfg
ctoepl/_clean_tables.py
ctoepl/ast_transforms.py
ctoepl/c_ast.py
ctoepl/c_generator.py
ctoepl/c_lexer.py
ctoepl/c_parser.py
ctoepl/epl_generator.py
ctoepl/lextab.py
ctoepl/plyparser.py
ctoepl/yacctab.py
ctoepl/ply/__init__.py
ctoepl/ply/cpp.py
ctoepl/ply/ctokens.py
ctoepl/ply/lex.py
ctoepl/ply/yacc.py
ctoepl/ply/ygen.py
utils/fake_libc_include/_ansi.h
utils/fake_libc_include/_fake_defines.h
utils/fake_libc_include/_fake_typedefs.h
utils/fake_libc_include/_syslist.h
utils/fake_libc_include/aio.h
utils/fake_libc_include/alloca.h
utils/fake_libc_include/ar.h
utils/fake_libc_include/argz.h
utils/fake_libc_include/assert.h
utils/fake_libc_include/complex.h
utils/fake_libc_include/cpio.h
utils/fake_libc_include/ctype.h
utils/fake_libc_include/dirent.h
utils/fake_libc_include/dlfcn.h
utils/fake_libc_include/endian.h
utils/fake_libc_include/envz.h
utils/fake_libc_include/errno.h
utils/fake_libc_include/fastmath.h
utils/fake_libc_include/fcntl.h
utils/fake_libc_include/features.h
utils/fake_libc_include/fenv.h
utils/fake_libc_include/float.h
utils/fake_libc_include/fmtmsg.h
utils/fake_libc_include/fnmatch.h
utils/fake_libc_include/ftw.h
utils/fake_libc_include/getopt.h
utils/fake_libc_include/glob.h
utils/fake_libc_include/grp.h
utils/fake_libc_include/iconv.h
utils/fake_libc_include/ieeefp.h
utils/fake_libc_include/inttypes.h
utils/fake_libc_include/iso646.h
utils/fake_libc_include/langinfo.h
utils/fake_libc_include/libgen.h
utils/fake_libc_include/libintl.h
utils/fake_libc_include/limits.h
utils/fake_libc_include/locale.h
utils/fake_libc_include/malloc.h
utils/fake_libc_include/math.h
utils/fake_libc_include/monetary.h
utils/fake_libc_include/mqueue.h
utils/fake_libc_include/ndbm.h
utils/fake_libc_include/netdb.h
utils/fake_libc_include/newlib.h
utils/fake_libc_include/nl_types.h
utils/fake_libc_include/paths.h
utils/fake_libc_include/poll.h
