Metadata-Version: 1.1
Name: c-to-epl
Version: 1.2
Summary: C to ePL Converter in Python
Home-page: https://github.com/xel-software/c-to-epl
Author: Xeline Software Development Team
Author-email: junk@mailinator.com
Maintainer: Xeline Software Development Team
License: BSD
Download-URL: https://github.com/xel-software/c-to-epl/archive/1.2.tar.gz
Platform: Cross Platform
Classifier: Development Status :: 5 - Production/Stable
Classifier: License :: OSI Approved :: BSD License
Classifier: Programming Language :: Python :: 2
Classifier: Programming Language :: Python :: 2.7
Classifier: Programming Language :: Python :: 3
Classifier: Programming Language :: Python :: 3.2
Classifier: Programming Language :: Python :: 3.3
Classifier: Programming Language :: Python :: 3.4
Classifier: Programming Language :: Python :: 3.5
Classifier: Programming Language :: Python :: 3.6
